LICENSE
MANIFEST.in
README.rst
setup.py
bin/csvfilter
csvfilter/__init__.py
csvfilter.egg-info/PKG-INFO
csvfilter.egg-info/SOURCES.txt
csvfilter.egg-info/dependency_links.txt
csvfilter.egg-info/top_level.txt