Metadata-Version: 1.0
Name: csvfilter
Version: 0.3
Summary: A command-line utility and Python API for manipulating CSV data, eg plucking columns and reordering them.  It's a bit like the unix utility 'cut'
Home-page: https://github.com/codeinthehole/csvfilter
Author: David Winterbottom
Author-email: david.winterbottom@gmail.com
License: MIT
Platform: UNKNOWN
